{"cameraMode":{"drawMode":0,"name":"Shaded","section":"Shading Mode"},"sceneLighting":true,"audioPlay":false,"sceneViewState":{"showFog":true,"showMaterialUpdate":false,"showSkybox":true,"showFlares":true,"showImageEffects":true,"showParticleSystems":true},"in2DMode":false,"pivot":{"x":-102.30586242675781,"y":0.33793163299560549,"z":-0.3071763515472412},"rotation":{"x":-0.2762533724308014,"y":-0.1571173220872879,"z":0.04582904651761055,"w":-0.9470469951629639},"size":239.8468780517578,"orthographic":false}